poetry_add_requirements_txt/__init__.py
poetry_add_requirements_txt/cli.py
poetry_add_requirements_txt/cli_uv.py
poetry_add_requirements_txt/utils.py
poetry_add_requirements_txt-1.5.4.dist-info/LICENSE
poetry_add_requirements_txt-1.5.4.dist-info/METADATA
poetry_add_requirements_txt-1.5.4.dist-info/WHEEL
poetry_add_requirements_txt-1.5.4.dist-info/entry_points.txt
poetry_add_requirements_txt-1.5.4.dist-info/RECORD
