Metadata-Version: 2.1
Name: poetry-add-requirements.txt
Version: 1.5.4
Summary: Add dependencies specified in requirements.txt file(s) to your Poetry / UV project
Home-page: https://github.com/tddschn/poetry-add-requirements.txt
License: MIT
Keywords: poetry,requirements.txt
Author: Xinyuan Chen
Author-email: 45612704+tddschn@users.noreply.github.com
Requires-Python: >=3.10,<4.0
Classifier: License :: OSI Approved :: MIT License
Classifier: Programming Language :: Python :: 3
Classifier: Programming Language :: Python :: 3.10
Classifier: Programming Language :: Python :: 3.11
Classifier: Programming Language :: Python :: 3.12
Classifier: Programming Language :: Python :: 3.13
Classifier: Topic :: Utilities
Requires-Dist: charset-normalizer (>=2.0.12,<3.0.0)
Project-URL: Bug Tracker, https://github.com/tddschn/poetry-add-requirements.txt/issues
Project-URL: Repository, https://github.com/tddschn/poetry-add-requirements.txt
